{"_type":"export","__export_format":4,"__export_date":"2020-04-16T19:43:51.316Z","__export_source":"insomnia.desktop.app:v7.1.1","resources":[{"_id":"req_6a603a47fafe40368483e9219e004f7d","authentication":{},"body":{"mimeType":"application/json","text":"{\n\t\"email\":\"fbc623@gmail.com\",\n\t\"password\":\"123456\"\n}"},"created":1587048085821,"description":"","headers":[{"id":"pair_61a25504bf28483b8225e4908aa02ec1","name":"Content-Type","value":"application/json"}],"isPrivate":false,"metaSortKey":-1587048085822,"method":"POST","modified":1587064745761,"name":"Create","parameters":[],"parentId":"fld_971df0f1458b46a28a66f36ad38db4a5","settingDisableRenderRequestBody":false,"settingEncodeUrl":true,"settingFollowRedirects":"global","settingRebuildPath":true,"settingSendCookies":true,"settingStoreCookies":true,"url":"{{ base_url  }}/sessions","_type":"request"},{"_id":"fld_971df0f1458b46a28a66f36ad38db4a5","created":1587048075293,"description":"","environment":{},"environmentPropertyOrder":null,"metaSortKey":-1587048075295,"modified":1587048075293,"name":"Sessions","parentId":"wrk_c1288f9eee0a442fb78e835b1ca557b8","_type":"request_group"},{"_id":"wrk_c1288f9eee0a442fb78e835b1ca557b8","created":1586786267251,"description":"","modified":1586786267251,"name":"GoBarber bootcamp 11","parentId":null,"_type":"workspace"},{"_id":"req_2401af660fd9422993784a5f2fb444d9","authentication":{"token":"{{ token  }}","type":"bearer"},"body":{"mimeType":"multipart/form-data","params":[{"description":"","fileName":"C:\\Users\\fbc62\\OneDrive\\Pictures\\perfil.jpg","id":"pair_c317af0a675d4ab392ee6a29312aca39","name":"avatar","type":"file","value":""}]},"created":1587061006553,"description":"","headers":[{"id":"pair_fa6654b600084f28bceaf3ab2ce375ee","name":"Content-Type","value":"multipart/form-data"}],"isPrivate":false,"metaSortKey":-1587061006553,"method":"PATCH","modified":1587061816527,"name":"Uptate Avatar","parameters":[],"parentId":"fld_3ec3b51cfa174aec83d9390397adbff5","settingDisableRenderRequestBody":false,"settingEncodeUrl":true,"settingFollowRedirects":"global","settingRebuildPath":true,"settingSendCookies":true,"settingStoreCookies":true,"url":"{{ base_url  }}/users/avatar","_type":"request"},{"_id":"fld_3ec3b51cfa174aec83d9390397adbff5","created":1587044908351,"description":"","environment":{},"environmentPropertyOrder":null,"metaSortKey":-1587044908351,"modified":1587044908351,"name":"Users","parentId":"wrk_c1288f9eee0a442fb78e835b1ca557b8","_type":"request_group"},{"_id":"req_0c860c7195af494fab91f0a0c484554c","authentication":{},"body":{"mimeType":"application/json","text":"{\n\t\"name\":\"fabiano\",\n\t\"email\":\"fbc623@gmail.com\",\n\t\"password\":\"123456\"\n}"},"created":1587044919399,"description":"","headers":[{"id":"pair_71d1dd8dd36f4d798b3b5c64298df0a5","name":"Content-Type","value":"application/json"}],"isPrivate":false,"metaSortKey":-1586684709949,"method":"POST","modified":1587046466336,"name":"Create","parameters":[],"parentId":"fld_3ec3b51cfa174aec83d9390397adbff5","settingDisableRenderRequestBody":false,"settingEncodeUrl":true,"settingFollowRedirects":"global","settingRebuildPath":true,"settingSendCookies":true,"settingStoreCookies":true,"url":"{{ base_url  }}/users","_type":"request"},{"_id":"req_425c8a6dc431498ead33e7d080470c44","authentication":{"token":"{{ token  }}","type":"bearer"},"body":{"mimeType":"application/json","text":"{\n\t\"provider_id\": \"4849a8fe-8006-4fad-9e23-aab96f2dca4d\",\n\t\"date\": \"{% now 'iso-8601', '' %}\" \n}"},"created":1586786302629,"description":"","headers":[{"id":"pair_71d1dd8dd36f4d798b3b5c64298df0a5","name":"Content-Type","value":"application/json"}],"isPrivate":false,"metaSortKey":-1586786302629,"method":"POST","modified":1587048966879,"name":"Create","parameters":[],"parentId":"fld_e368da6b8945454ab65bb192a11d788b","settingDisableRenderRequestBody":false,"settingEncodeUrl":true,"settingFollowRedirects":"global","settingRebuildPath":true,"settingSendCookies":true,"settingStoreCookies":true,"url":"{{ base_url  }}/appointments","_type":"request"},{"_id":"fld_e368da6b8945454ab65bb192a11d788b","created":1586786290889,"description":"","environment":{},"environmentPropertyOrder":null,"metaSortKey":-1586786290889,"modified":1586786290889,"name":"Appointments","parentId":"wrk_c1288f9eee0a442fb78e835b1ca557b8","_type":"request_group"},{"_id":"req_e5f905665ee74a8d9f03bca88931bb16","authentication":{"disabled":false,"token":"{{ token  }}","type":"bearer"},"body":{},"created":1586804575604,"description":"","headers":[],"isPrivate":false,"metaSortKey":-1586583117269,"method":"GET","modified":1587050063716,"name":"List","parameters":[],"parentId":"fld_e368da6b8945454ab65bb192a11d788b","settingDisableRenderRequestBody":false,"settingEncodeUrl":true,"settingFollowRedirects":"global","settingRebuildPath":true,"settingSendCookies":true,"settingStoreCookies":true,"url":"{{ base_url  }}/appointments","_type":"request"},{"_id":"env_e2efd27a883d1072a8357c33fd8989e295ed8442","color":null,"created":1586786267366,"data":{},"dataPropertyOrder":null,"isPrivate":false,"metaSortKey":1586786267366,"modified":1586786267366,"name":"Base Environment","parentId":"wrk_c1288f9eee0a442fb78e835b1ca557b8","_type":"environment"},{"_id":"jar_e2efd27a883d1072a8357c33fd8989e295ed8442","cookies":[],"created":1586786267369,"modified":1586786267369,"name":"Default Jar","parentId":"wrk_c1288f9eee0a442fb78e835b1ca557b8","_type":"cookie_jar"},{"_id":"env_09addade2cd749c7955b17f54421a54a","color":"#7d69cb","created":1586786322447,"data":{"base_url":"http://localhost:3333","token":"eyJhbGciOiJIUzI1NiIsInR5cCI6IkpXVCJ9.eyJpYXQiOjE1ODcwNDg5NDIsImV4cCI6MTU4NzEzNTM0Miwic3ViIjoiODU1ZDQ0ZWMtZWQ1Mi00ODcyLTg1MjEtNjg4MDYxZTlhZjc3In0.hRUZeDeV8eGYQMIdDMTaVoacPd6o3Wf_-t32UClh4rs"},"dataPropertyOrder":{"&":["base_url","token"]},"isPrivate":false,"metaSortKey":1586786322447,"modified":1587048952456,"name":"Dev","parentId":"env_e2efd27a883d1072a8357c33fd8989e295ed8442","_type":"environment"}]}